uvlpy/__init__.py
uvlpy/uvlpy.py
uvlpy-0.1.2.dist-info/licenses/LICENSE
uvlpy-0.1.2.dist-info/METADATA
uvlpy-0.1.2.dist-info/WHEEL
uvlpy-0.1.2.dist-info/top_level.txt
uvlpy-0.1.2.dist-info/RECORD
