Metadata-Version: 2.4
Name: uvlpy
Version: 0.1.2
Summary: UV abused for your pleasure
Author-email: Vasyl Bodnar <vasylbodnar@outlook.com>
License-Expression: BSD-3-Clause
Project-URL: Homepage, https://github.com/Vasyl-Bodnar/uvlpy
Keywords: constraint,solver,uv
Classifier: Programming Language :: Python :: 3
Requires-Python: >=3.10
License-File: LICENSE
Dynamic: license-file
